fds/__init__.py
fds/sdk/__init__.py
fds/sdk/WatchlistAPIforDigitalPortals/__init__.py
fds/sdk/WatchlistAPIforDigitalPortals/api_client.py
fds/sdk/WatchlistAPIforDigitalPortals/configuration.py
fds/sdk/WatchlistAPIforDigitalPortals/exceptions.py
fds/sdk/WatchlistAPIforDigitalPortals/model_utils.py
fds/sdk/WatchlistAPIforDigitalPortals/rest.py
fds/sdk/WatchlistAPIforDigitalPortals/api/__init__.py
fds/sdk/WatchlistAPIforDigitalPortals/api/watchlist_api.py
fds/sdk/WatchlistAPIforDigitalPortals/apis/__init__.py
fds/sdk/WatchlistAPIforDigitalPortals/model/__init__.py
fds/sdk/WatchlistAPIforDigitalPortals/model/attributes_member.py
fds/sdk/WatchlistAPIforDigitalPortals/model/cursor_based_pagination_output_object.py
fds/sdk/WatchlistAPIforDigitalPortals/model/cursor_based_pagination_output_object_without_total.py
fds/sdk/WatchlistAPIforDigitalPortals/model/error_meta_object.py
fds/sdk/WatchlistAPIforDigitalPortals/model/error_object.py
fds/sdk/WatchlistAPIforDigitalPortals/model/inline_object.py
fds/sdk/WatchlistAPIforDigitalPortals/model/inline_object1.py
fds/sdk/WatchlistAPIforDigitalPortals/model/inline_object2.py
fds/sdk/WatchlistAPIforDigitalPortals/model/inline_object3.py
fds/sdk/WatchlistAPIforDigitalPortals/model/inline_object4.py
fds/sdk/WatchlistAPIforDigitalPortals/model/inline_object5.py
fds/sdk/WatchlistAPIforDigitalPortals/model/inline_object6.py
fds/sdk/WatchlistAPIforDigitalPortals/model/inline_response200.py
fds/sdk/WatchlistAPIforDigitalPortals/model/inline_response2001.py
fds/sdk/WatchlistAPIforDigitalPortals/model/inline_response2001_data.py
fds/sdk/WatchlistAPIforDigitalPortals/model/inline_response2002.py
fds/sdk/WatchlistAPIforDigitalPortals/model/inline_response2002_data.py
fds/sdk/WatchlistAPIforDigitalPortals/model/inline_response2003.py
fds/sdk/WatchlistAPIforDigitalPortals/model/inline_response2004.py
fds/sdk/WatchlistAPIforDigitalPortals/model/inline_response2004_data.py
fds.sdk.WatchlistAPIforDigitalPortals-0.9.5.dist-info/LICENSE
fds.sdk.WatchlistAPIforDigitalPortals-0.9.5.dist-info/METADATA
fds.sdk.WatchlistAPIforDigitalPortals-0.9.5.dist-info/WHEEL
fds.sdk.WatchlistAPIforDigitalPortals-0.9.5.dist-info/top_level.txt
fds.sdk.WatchlistAPIforDigitalPortals-0.9.5.dist-info/RECORD
