Metadata-Version: 2.1
Name: fds.sdk.WatchlistAPIforDigitalPortals
Version: 0.9.5
Summary: Watchlist API for Digital Portals client library for Python
Home-page: https://github.com/FactSet/enterprise-sdk/tree/main/code/python/WatchlistAPIforDigitalPortals/v2
Author: FactSet Research Systems
License: Apache-2.0
Keywords: FactSet,API,SDK
Platform: UNKNOWN
Requires-Python: >=3.7
License-File: LICENSE
Requires-Dist: urllib3 (>=1.25.3)
Requires-Dist: python-dateutil
Requires-Dist: fds.sdk.utils (>=1.0.0)
